fw_http_parser/__init__.py
fw_http_parser/fw_http_parser.py
fw_http_parser-0.3.2.dist-info/LICENSE
fw_http_parser-0.3.2.dist-info/METADATA
fw_http_parser-0.3.2.dist-info/WHEEL
fw_http_parser-0.3.2.dist-info/top_level.txt
fw_http_parser-0.3.2.dist-info/RECORD
