Metadata-Version: 2.1
Name: fw-http-parser
Version: 0.3.2
Summary: Parsing data from a socket connection
Home-page: https://github.com/fwRelik/fw-http-parser
Author: fwRelik
Author-email: relik.fw@gmail.com
Classifier: Programming Language :: Python
Classifier: Operating System :: OS Independent
Requires-Python: >=3.6
License-File: LICENSE
